seqinf/__init__.py
seqinf/collector.py
seqinf/diagnostic.py
seqinf/dropout.py
seqinf/flow.py
seqinf/posterior.py
seqinf/sequential.py
seqinf/util.py
seqinf/estimators/nflows_bflow.py
seqinf/methods/__init__.py
seqinf/methods/posterior.py
seqinf/net_builders/bflow.py
seqinf/trainers/bnpe_base.py
seqinf/trainers/bnpe_c.py
seqinf/transforms/bflow.py
seqinf/transforms/made.py
seqinf-0.2.1.dist-info/METADATA
seqinf-0.2.1.dist-info/WHEEL
seqinf-0.2.1.dist-info/top_level.txt
seqinf-0.2.1.dist-info/RECORD
