Metadata-Version: 2.1
Name: seqinf
Version: 0.2.1
Summary: Sequential inference abstractions
Author-email: Sam Griesemer <samgriesemer+git@gmail.com>
Project-URL: Homepage, https://doc.olog.io/<project-name>
Project-URL: Documentation, https://doc.olog.io/<project-name>
Project-URL: Repository, https://git.olog.io/olog/<project-name>
Project-URL: Issues, https://git.olog.io/olog/<project-name>/issues
Keywords: simulation,machine learning,statistics
Classifier: Programming Language :: Python :: 3.12
Classifier: License :: OSI Approved :: MIT License
Classifier: Operating System :: OS Independent
Classifier: Development Status :: 3 - Alpha
Classifier: Intended Audience :: Developers
Requires-Python: >=3.10
Requires-Dist: sbi
Requires-Dist: sbibm
Provides-Extra: tests
Requires-Dist: pytest; extra == "tests"
Provides-Extra: docs
Requires-Dist: sphinx; extra == "docs"
Requires-Dist: sphinx-togglebutton; extra == "docs"
Requires-Dist: sphinx-autodoc-typehints; extra == "docs"
Requires-Dist: furo; extra == "docs"
Requires-Dist: myst-parser; extra == "docs"
Provides-Extra: jupyter
Requires-Dist: jupyter; extra == "jupyter"
Requires-Dist: ipykernel; extra == "jupyter"
